[{"56beb4343aeaaa14008c925b": " 308"}, {"56beb4343aeaaa14008c925c": " 136,"}, {"56beb4343aeaaa14008c925d": " (118),"}, {"56beb4343aeaaa14008c925e": " patru"}, {"56beb4343aeaaa14008c925f": " Mario Addison"}, {"56d6f3500d65d21400198290": " 24"}, {"56d6f3500d65d21400198291": " Mario Addison"}, {"56d6f3500d65d21400198292": " Thomas Davis și Luke Kuechly."}, {"56d6f3500d65d21400198293": " patru"}, {"56d6f3500d65d21400198294": " Kurt Coleman,"}, {"56d9992fdc89441400fdb59c": " 24"}, {"56d9992fdc89441400fdb59e": " Kony Ealy,"}, {"56d9992fdc89441400fdb59f": " Kuechly"}, {"56d9992fdc89441400fdb5a0": " patru"}, {"56beb7953aeaaa14008c92ab": " Pittsburgh Steelers"}, {"56beb7953aeaaa14008c92ac": " 11"}, {"56beb7953aeaaa14008c92ad": " New England Patriots,"}, {"56beb7953aeaaa14008c92ae": " 20–18"}, {"56beb7953aeaaa14008c92af": " 17 secunde"}, {"56bf36b93aeaaa14008c9561": " Pittsburgh Steelers"}, {"56bf36b93aeaaa14008c9562": " 11 puncte"}, {"56bf36b93aeaaa14008c9563": " New England Patriots,"}, {"56bf36b93aeaaa14008c9564": " 17"}, {"56bf36b93aeaaa14008c9565": " Manning"}, {"56d7018a0d65d214001982c2": " Pittsburgh Steelers"}, {"56d7018a0d65d214001982c3": " 11"}, {"56d7018a0d65d214001982c5": " New England Patriots,"}, {"56d99f99dc89441400fdb628": " Pittsburgh Steelers"}, {"56d99f99dc89441400fdb629": " New England Patriots,"}, {"56d99f99dc89441400fdb62c": " 17"}, {"56beb86b3aeaaa14008c92bd": " 39 de ani."}, {"56beb86b3aeaaa14008c92be": " John Elway,"}, {"56beb86b3aeaaa14008c92bf": " 38 de ani"}, {"56beb86b3aeaaa14008c92c0": " Vicepreședintele Executiv pentru Operațiuni de Fotbal și Managerul General"}, {"56beb86b3aeaaa14008c92c1": " echipa Broncos"}, {"56bf3fd53aeaaa14008c9591": " Broncos"}, {"56bf3fd53aeaaa14008c9592": " John Elway,"}, {"56bf3fd53aeaaa14008c9593": " 38 de ani"}, {"56bf3fd53aeaaa14008c9594": " John Elway,"}, {"56bf3fd53aeaaa14008c9595": " două"}, {"56d704430d65d214001982de": " două"}, {"56d704430d65d214001982e0": "Peyton Manning"}, {"56d704430d65d214001982e1": "Peyton Manning"}, {"56d704430d65d214001982e2": " Super Bowl XXXIII"}, {"56d9a0eadc89441400fdb63e": "Peyton Manning"}, {"56d9a0eadc89441400fdb63f": " 39 de ani."}, {"56d9a0eadc89441400fdb640": " John Elway,"}, {"56bec6ac3aeaaa14008c93fd": " șase"}, {"56bec6ac3aeaaa14008c93fe": " imnul național,"}, {"56bec6ac3aeaaa14008c93ff": " Premiilor Academiei Americane de Film"}, {"56bec6ac3aeaaa14008c9400": " Limbajul American al Semnelor"}, {"56bec6ac3aeaaa14008c9401": " Limbajul American al Semnelor"}, {"56d20650e7d4791d00902614": "Lady Gaga,"}, {"56d20650e7d4791d00902615": " Marlee Matlin"}, {"56d7253b0d65d214001983d4": "Lady Gaga,"}, {"56d7253b0d65d214001983d5": " Marlee Matlin"}, {"56d9c455dc89441400fdb7c4": "Lady Gaga,"}, {"56d9c455dc89441400fdb7c5": " șase"}, {"56d9c455dc89441400fdb7c6": " Marlee Matlin"}, {"56beca913aeaaa14008c946d": " 24"}, {"56beca913aeaaa14008c946e": " echipa Carolina"}, {"56beca913aeaaa14008c946f": " Josh Norman."}, {"56beca913aeaaa14008c9470": " Anderson"}, {"56beca913aeaaa14008c9471": " Bennie Fowler"}, {"56d726b60d65d214001983ea": " Miller"}, {"56d726b60d65d214001983eb": " Ward,"}, {"56d726b60d65d214001983ec": " Newton"}, {"56d726b60d65d214001983ed": " Josh Norman."}, {"56d726b60d65d214001983ee": " 3:08 minute"}, {"56d9cb47dc89441400fdb832": " 4:51 minute"}, {"56d9cb47dc89441400fdb833": " Miller"}, {"56d9cb47dc89441400fdb834": " Ward,"}, {"56d9cb47dc89441400fdb835": " trei"}, {"56d9cb47dc89441400fdb836": " Anderson"}, {"57339c16d058e614000b5ec5": " Ogród Saski"}, {"57339c16d058e614000b5ec6": " Ogród Saski"}, {"57339c16d058e614000b5ec7": " între anii 1870 și 1939,"}, {"57339c16d058e614000b5ec8": " Momus,"}, {"57339c16d058e614000b5ec9": " Teatrul Wojciech Bogusławski"}, {"5733a32bd058e614000b5f32": " Polonia Varșovia,"}, {"5733a32bd058e614000b5f33": " 1946,"}, {"5733a32bd058e614000b5f34": " două"}, {"5733a32bd058e614000b5f35": " pe strada Konwiktorska,"}, {"5733a32bd058e614000b5f36": " situației sale financiare dezastruoase."}, {"57338007d058e614000b5bda": " multicultural."}, {"57338007d058e614000b5bdb": " 711.988"}, {"57338007d058e614000b5bdc": " 56,2%"}, {"57338007d058e614000b5bdd": " 2,8%"}, {"57338007d058e614000b5bde": " Revoltei din Varșovia din 1944."}, {"573380e0d058e614000b5be9": " comuna"}, {"573380e0d058e614000b5bea": " districte sau powiat."}, {"573380e0d058e614000b5beb": " Cracovia"}, {"5733834ed058e614000b5c26": " 1817,"}, {"5733834ed058e614000b5c27": " controlul comunist postbelic"}, {"5733834ed058e614000b5c28": " aprilie 1991,"}, {"5733834ed058e614000b5c29": " 374"}, {"5733834ed058e614000b5c2a": " Partidului Uniunii Muncitorilor din Polonia"}, {"56dde1d966d3e219004dad8d": " Rollo,"}, {"56de0daecffd8e1900b4b595": " Drogo,"}, {"56de0daecffd8e1900b4b596": " William Braț de Fier,"}, {"56de0f6a4396321400ee257f": " Seljuk."}, {"56de10b44396321400ee2593": " Afranji,"}, {"56de10b44396321400ee2594": " Oursel"}, {"56de10b44396321400ee2595": " Sassoun și Taron"}, {"56de49564396321400ee277a": " Africii."}, {"56dfa0d84a1a83140091ebb7": " 1943."}, {"56dfa0d84a1a83140091ebb8": " Conferința Generală de Măsuri și Greutăți"}, {"56dfa0d84a1a83140091ebb9": " hoteluri din New York,"}, {"56dfa0d84a1a83140091ebba": " „cercetător nebun”"}, {"56e0bb9f7aa994140058e6cb": " Brevetele"}, {"56e0bb9f7aa994140058e6cc": " 1943."}, {"56e0bb9f7aa994140058e6cd": " unitatea SI pentru densitatea de fluxul magnetic Tesla"}, {"56e0bb9f7aa994140058e6ce": " anii 1990s"}, {"56e0bb9f7aa994140058e6cf": " realizările sale și talentul său de bun animator,"}, {"56dfb5777aa994140058e021": " Robert Lane și Benjamin Vail,"}, {"56dfb5777aa994140058e022": " Tesla Electric Light & Manufacturing."}, {"56dfb5777aa994140058e023": " iluminat electric"}, {"56dfb5777aa994140058e024": " brevete"}, {"56dfb5777aa994140058e025": " comutatoare pentru mașini dinamo-electrice,"}, {"56e0d6cf231d4119001ac420": " Tesla Electric Light & Manufacturing."}, {"56e0d6cf231d4119001ac421": " 1886"}, {"56e0d6cf231d4119001ac422": " Tesla Electric Light & Manufacturing."}, {"56e0d6cf231d4119001ac423": " Compania a instalat sisteme de iluminat pe bază de arc electric"}, {"56e0d6cf231d4119001ac424": " Tesla,"}, {"56e0fc3f7aa994140058e877": " 1900,"}, {"56e0fc3f7aa994140058e878": " Guglielmo Marconi"}, {"56e0fc3f7aa994140058e879": " 1901,"}, {"56e0fc3f7aa994140058e87a": " 1943,"}, {"56e0fc3f7aa994140058e87b": " Curții Supreme a Statelor Unite"}, {"56e10aa5cd28a01900c674b3": " 38"}, {"56e10aa5cd28a01900c674b4": " Edison"}, {"56e10aa5cd28a01900c674b5": " 1937)."}, {"56e1254ae3433e1400422c66": " „O mașină care să pună capăt războiului”,"}, {"56e1254ae3433e1400422c67": " îndoielnice"}, {"56e1254ae3433e1400422c68": " războiului”,"}, {"56e16182e3433e1400422e28": "Teoria complexității computaționale"}, {"56e16182e3433e1400422e29": " dificultatea lor inerentă,"}, {"56e16182e3433e1400422e2a": " O problemă computațională"}, {"56e181d9e3433e1400422fa0": " (string)"}, {"56e181d9e3433e1400422fa1": " alfabetul binar"}, {"56e181d9e3433e1400422fa2": " (string)"}, {"56e181d9e3433e1400422fa3": " notație binară,"}, {"56e181d9e3433e1400422fa4": " codificarea listelor lor de adiacență în binar."}, {"56e1a0dccd28a01900c67a2e": " sub forma unor probleme de decizie."}, {"56e1a0dccd28a01900c67a2f": " setul de triplete"}, {"56e1b62ecd28a01900c67aa3": " („da” sau „nu”)."}, {"56e1b62ecd28a01900c67aa4": " dificultate,"}, {"56e1b62ecd28a01900c67aa5": " DTIME(f(n))."}, {"56e1b62ecd28a01900c67aa6": " DTIME(f(n))."}, {"56e1ee4de3433e1400423210": " inegală"}, {"56e1ee4de3433e1400423211": " restrângă într-o singură clasă."}, {"56e1ee4de3433e1400423212": " într-o singură clasă."}, {"56e1ee4de3433e1400423214": " oricare dintre aceste clase este inegală"}, {"56e7586d37bdd419002c3eb3": " una dintre cele mai obișnuite"}, {"56e7586d37bdd419002c3eb4": " Majoritatea țărilor vestice,"}, {"56e7586d37bdd419002c3eb5": " Statele Unite"}, {"56e7586d37bdd419002c3eb6": " Curții Supreme ale Statelor Unite"}, {"56e7586d37bdd419002c3eb7": " durere fizică)"}, {"56e7788200c9c71400d77180": " sindicate precum ATL, NUT sau NASUWT,"}, {"56e7788200c9c71400d77181": " descreștere,"}, {"56e7788200c9c71400d77182": " 2005 și 2010."}, {"56e7788200c9c71400d77183": " sindicate"}, {"56e7788200c9c71400d77184": " îngrijorare"}, {"56e7796637bdd419002c3ffd": " fiecare stat"}, {"56e7796637bdd419002c3ffe": " zece ani."}, {"56e7796637bdd419002c3fff": " diplomă de licență,"}, {"56e7796637bdd419002c4000": " Numeroase școlile alternative"}, {"56e7796637bdd419002c4001": " No Child Left Behind"}, {"56e77cee00c9c71400d771a8": " guru,"}, {"56e77cee00c9c71400d771a9": " puternic,"}, {"56e77cee00c9c71400d771aa": " discipolilor săi."}, {"56e77cee00c9c71400d771ab": " vest"}, {"56e77da237bdd419002c403b": " Lama."}, {"56e77da237bdd419002c403c": " renască,"}, {"56e77da237bdd419002c403d": " Tulku."}, {"56e77da237bdd419002c403e": " mai multe ori,"}, {"56e77da237bdd419002c403f": " phowa și siddhi"}, {"56f8094aa6d7ea1400e17391": " 1519."}, {"56f8094aa6d7ea1400e17392": " Studenții"}, {"56f8094aa6d7ea1400e17393": " Psalmii."}, {"56f8094aa6d7ea1400e17394": " 1520:"}, {"56f8094aa6d7ea1400e17395": " Despre libertatea unui creștin."}, {"56f84485aef2371900625f71": " vara anului 1521,"}, {"56f84485aef2371900625f72": " aceasta este un cadou,"}, {"56f84485aef2371900625f73": " un cadou,"}, {"56f84485aef2371900625f74": " Teza lui Despre confesiune,"}, {"56f84485aef2371900625f75": " că își pot încălca jurămintele"}, {"56f86e91aef2371900626067": " publicații în limba germană"}, {"56f86e91aef2371900626068": " bibliei."}, {"56f86e91aef2371900626069": " evoluția limbii și literaturii germane."}, {"56f86e91aef237190062606a": " Lucas Cranach,"}, {"56f86e91aef237190062606b": " William Tyndale"}, {"56f8720eaef237190062608f": " „Ein neues Lied wir heben an\""}, {"56f8720eaef2371900626090": " viziuni luterane,"}, {"56f8720eaef2371900626091": " „Ein neues Lied wir heben an\""}, {"56f8720eaef2371900626092": " John C. Messenger"}, {"56f8720eaef2371900626093": " „Flung to the Heedless Winds\""}, {"56f8ca289b226e1400dd1007": " o bucată de hârtie"}, {"56f8ca289b226e1400dd1008": " latină,"}, {"56f8ca289b226e1400dd1009": " „Suntem cerșetori”"}, {"5705f7c875f01819005e77dc": " al treilea"}, {"5705f7c875f01819005e77dd": " zone vaste"}, {"5705f7c875f01819005e77de": " suburbane"}, {"5705f7c875f01819005e77df": " comunitățile sale suburbane mari,"}, {"5705f7c875f01819005e77e0": " metropolitană internațională"}, {"5706074552bb8914006897d4": " Zone Statistice Metropolitane,"}, {"5706074552bb8914006897d5": " două"}, {"5706074552bb8914006897d6": " cinci milioane"}, {"5706074552bb8914006897d7": " Regiunea Graniței Sudice."}, {"5706074552bb8914006897d8": " 17.786.419,"}, {"570610b275f01819005e792a": " Aeroportul Internațional Los Angeles,"}, {"570610b275f01819005e792b": " Aeroportul Van Nuys cel mai aglomerat aeroport destinat aviației generale;"}, {"570610b275f01819005e792c": " al treilea"}, {"570610b275f01819005e792d": " Aeroportul Internațional San Diego"}, {"570610b275f01819005e792e": " Aeroportul Van Nuys"}, {"5706143575f01819005e7950": " NFL"}, {"5706143575f01819005e7951": " NBA"}, {"5706143575f01819005e7952": " MLB"}, {"5706143575f01819005e7953": " (Los Angeles Kings,"}, {"5706143575f01819005e7954": " (LA Galaxy)."}, {"5706149552bb891400689880": " LA Galaxy și Chivas"}, {"5706149552bb891400689881": " două"}, {"5706149552bb891400689882": " 2014,"}, {"5706149552bb891400689883": " Centrul StubHub"}, {"5706149552bb891400689884": " 2018."}, {"570966e0200fba1400367f4f": " MPEG-2"}, {"570966e0200fba1400367f50": " Dolby Digital"}, {"570966e0200fba1400367f51": " MPEG-4,"}, {"570966e0200fba1400367f52": " OpenTV,"}, {"570966e0200fba1400367f53": " DVB-S2 standard."}, {"570967c4ed30961900e840ba": " 1998"}, {"570967c4ed30961900e840bb": " Astra 2A"}, {"570967c4ed30961900e840bc": " Eutelsat 1"}, {"570967c4ed30961900e840bd": " sute"}, {"570967c4ed30961900e840be": " 28.5°E"}, {"57096b66200fba1400367fa7": " 8 februarie 2007,"}, {"57096b66200fba1400367fa8": " martie"}, {"57096b66200fba1400367fa9": " terestră digitală,"}, {"57096b66200fba1400367faa": " Virgin Media."}, {"57096b66200fba1400367fab": " Liga Engleză de Fotbal Premier League),"}, {"57097c8fed30961900e841f2": " „Welfare Cash Card"}, {"57097c8fed30961900e841f3": " bunurilor „esențiale”."}, {"57097c8fed30961900e841f4": " „adesea dăunător”,"}, {"57097c8fed30961900e841f5": " „facturile Sky TV reclamanților"}, {"57097c8fed30961900e841f6": " ar demasca prezența unui bărbat în casa femeii."}, {"57097d63ed30961900e841fc": " £30m"}, {"57097d63ed30961900e841fd": " nu există indicii"}, {"57097d63ed30961900e841fe": " Virgin Media"}, {"57097d63ed30961900e841ff": " BSkyB cât și Virgin Media"}, {"57097d63ed30961900e84200": " transportul respectivelor canalele de bază."}, {"570d28bdb3d812140066d4a3": " Partidul Muncii"}, {"570d28bdb3d812140066d4a4": " Partidul Verde,"}, {"570d28bdb3d812140066d4a5": " Partidul Național"}, {"570d28bdb3d812140066d4a6": " Partidul Verde,"}, {"570d28bdb3d812140066d4a7": " Partidul Muncii"}, {"570d2f5bfed7b91900d45ccf": " 1975,"}, {"570d2f5bfed7b91900d45cd0": " constituției coloniale"}, {"570d2f5bfed7b91900d45cd1": " Parlamentul Victoriei,"}, {"570d2f5bfed7b91900d45cd2": " „adânc înrădăcinate”"}, {"570d2f5bfed7b91900d45cd3": " Legea Constituției Victoriene"}, {"570d3468b3d812140066d543": " Ford, Toyota și Holden;"}, {"570d3468b3d812140066d544": " februarie 2014"}, {"570d3468b3d812140066d545": " octombrie 2016)."}, {"570d3468b3d812140066d546": " octombrie 2016)."}, {"570d3468b3d812140066d547": " Ford"}, {"570d47b8b3d812140066d62d": " 1.600 mm"}, {"570d47b8b3d812140066d62e": " 1.435 mm"}, {"570d47b8b3d812140066d62f": " ecartament îngust de 760 mm"}, {"570d47b8b3d812140066d630": " zonele montane."}, {"570d47b8b3d812140066d631": " patru"}, {"570d4a6bfed7b91900d45e13": " 1788,"}, {"570d4a6bfed7b91900d45e14": " New South Wales"}, {"570d4a6bfed7b91900d45e15": " New Holland,"}, {"570d4a6bfed7b91900d45e16": " Sydney."}, {"57107d73b654c5140001f91d": " Edictul din Fontainebleau"}, {"57107d73b654c5140001f91e": " (1685),"}, {"57107d73b654c5140001f91f": " Louis al XIV-lea,"}, {"57107d73b654c5140001f920": " 500.000"}, {"5710eca0a58dae1900cd6b3a": " Districtul Inferior Norfolk."}, {"5710eca0a58dae1900cd6b3b": " Districtul Inferior Norfolk."}, {"5710eca0a58dae1900cd6b3c": " Orașul Manakin,"}, {"5710eca0a58dae1900cd6b3d": " 390"}, {"5710eca0a58dae1900cd6b3e": " 12 mai 1705"}, {"57111380a58dae1900cd6bd6": " Jacques Lefevre"}, {"57111380a58dae1900cd6bd7": " Geneva."}, {"57111380a58dae1900cd6bd8": " 1530."}, {"57111380a58dae1900cd6bd9": " William Farel"}, {"57111380a58dae1900cd6bda": " Jean Cauvin"}, {"57111713a58dae1900cd6c00": " rapid"}, {"57111713a58dae1900cd6c01": " rapid"}, {"57111713a58dae1900cd6c02": " E.I. du Pont,"}, {"57111713a58dae1900cd6c03": " secolul al nouăsprezecelea."}, {"57111713a58dae1900cd6c04": " Eleutherian Mills."}, {"57111b95a58dae1900cd6c50": "Frederick William,"}, {"57111b95a58dae1900cd6c51": " Lothar de Maizière"}, {"57111b95a58dae1900cd6c52": " Adolf Galland,"}, {"57111b95a58dae1900cd6c53": " Lothar de Maizière"}, {"57111b95a58dae1900cd6c54": " Ministrul Federal de Interne"}, {"571144d1a58dae1900cd6d6e": " reactor nuclear,"}, {"571144d1a58dae1900cd6d6f": " cameră de combustie,"}, {"571144d1a58dae1900cd6d70": " energia solară"}, {"571144d1a58dae1900cd6d71": " electric"}, {"57114667a58dae1900cd6d80": " indicatorul"}, {"57114667a58dae1900cd6d81": " 1851,"}, {"57114667a58dae1900cd6d82": " Charles Richard,"}, {"57114667a58dae1900cd6d83": " Charles Richard,"}, {"57114667a58dae1900cd6d84": " Expoziției din Londra"}, {"57114e8d50c2381900b54a5b": " lichidul de lucru."}, {"57114e8d50c2381900b54a5c": " 565 °C"}, {"57114e8d50c2381900b54a5d": " oțelului inoxidabil),"}, {"57114e8d50c2381900b54a5f": " 63%,"}, {"57114e8d50c2381900b54a5e": " 30 °C."}, {"57115bf350c2381900b54a93": " Energiprojekt AB"}, {"57115bf350c2381900b54a94": " Suedia"}, {"57115bf350c2381900b54a95": " 5"}, {"57115bf350c2381900b54a96": " 4 kg"}, {"57115bf350c2381900b54a97": " 27-30%"}, {"57115ff82419e314009555c3": " (discuri rotative)"}, {"57115ff82419e314009555c4": " un arbore motor,"}, {"57115ff82419e314009555c5": " (discuri statice)"}, {"57115ff82419e314009555c6": " carcasa turbinei."}, {"57115ff82419e314009555c7": " 3600 rotații pe minut (RPM)"}, {"571c8539dd7acb1400e4c0e2": " 1773"}, {"571c8539dd7acb1400e4c0e3": " 1774,"}, {"571c8539dd7acb1400e4c0e4": " lucrarea sa a fost publicată prima."}, {"571c8539dd7acb1400e4c0e5": " Antoine Lavoisier,"}, {"571c8539dd7acb1400e4c0e6": " teoriei flogisticului referitoare la combustie și coroziune"}, {"571c9348dd7acb1400e4c114": " James Dewar"}, {"571c9348dd7acb1400e4c115": " 1891"}, {"571c9348dd7acb1400e4c116": " 1895,"}, {"571c9348dd7acb1400e4c118": " oxiacetilenică"}, {"571cb27fdd7acb1400e4c132": "Paleoclimatologii"}, {"571cb27fdd7acb1400e4c133": " clima cu milioane de ani în urmă"}, {"571cb27fdd7acb1400e4c134": " 12%"}, {"571cb27fdd7acb1400e4c135": " oxigen-18"}, {"571cb27fdd7acb1400e4c136": " climat mai cald."}, {"571cbe35dd7acb1400e4c13c": " 687 și 760 nm."}, {"571cbe35dd7acb1400e4c13d": " ciclului carbonului de pe sateliți la nivel global."}, {"571cbe35dd7acb1400e4c13e": " platformă de satelit."}, {"571cbe35dd7acb1400e4c13f": " gradul de reflexie"}, {"571cbe35dd7acb1400e4c140": " teledetecția"}, {"571cd3b55efbb31900334e03": " camere de oxigen"}, {"571cd3b55efbb31900334e04": " monoxidului de carbon"}, {"571cd3b55efbb31900334e05": " bacteriile anaerobe"}, {"571cd3b55efbb31900334e06": " Boala de decompresie"}, {"5725bad5271a42140099d0bd": " 6 octombrie 1973,"}, {"5725bad5271a42140099d0be": " Iranul"}, {"5725bad5271a42140099d0bf": " zece ori mai mult”."}, {"5725bad5271a42140099d0c0": " Iranul"}, {"5725bad5271a42140099d0c1": " [prețul țițeiului] va crește..."}, {"5726241189a1e219009ac2de": "Embargoul"}, {"5726241189a1e219009ac2df": " auto."}, {"5726241189a1e219009ac2e0": " macroeconomice"}, {"5726241189a1e219009ac2e1": " regiunea arctică."}, {"5726241189a1e219009ac2e2": " cinci până la zece ani"}, {"57264d9edd62a815002e80fe": " William E. Simon"}, {"57264d9edd62a815002e80ff": " 1973,"}, {"57264d9edd62a815002e8100": " pentru coordonarea consecințelor embargo-ului."}, {"57264d9edd62a815002e8101": " 20%"}, {"572650325951b619008f6fa9": "Criza energetică"}, {"572650325951b619008f6faa": " realitățile pieței și pe cele tehnologice."}, {"572650325951b619008f6fab": " congresul și președinții"}, {"572659535951b619008f703f": " La un deceniu după criza petrolului din 1973,"}, {"572659535951b619008f7040": " Datsun)"}, {"572659535951b619008f7041": " aerul condiționat,"}, {"572659535951b619008f7042": " (Acura, Lexus respectiv Infiniti)"}, {"5725c604271a42140099d185": " Nicholas E. Golovin,"}, {"5725c604271a42140099d186": " iulie 1961,"}, {"5725c604271a42140099d187": " Manned Spacecraft Center"}, {"5725c604271a42140099d188": " Joseph Shea,"}, {"5725c604271a42140099d189": " modulului hibrid EOR-LOR."}, {"5725d79e89a1e219009abf90": " primul CSM Bloc II și LM"}, {"5725d79e89a1e219009abf91": " un nou costum spațial Apollo,"}, {"5725d79e89a1e219009abf92": " Tradiționala cască"}, {"5725d79e89a1e219009abf93": " cu răcire cu apă."}, {"5725d79e89a1e219009abf94": " Comandant (CDR – Commander),"}, {"5725db4aec44d21400f3d6bd": " America de Nord și în camera de altitudine"}, {"5725db4aec44d21400f3d6be": "Grissom, White, și Chaffee"}, {"5725db4aec44d21400f3d6bf": " o numărătoare inversă"}, {"5725db4aec44d21400f3d6c0": " America de Nord"}, {"5725dc1638643c19005ace01": " probleme de comunicație"}, {"5725dc1638643c19005ace02": " 27 ianuarie 1967"}, {"5725dc1638643c19005ace03": " izbucnit un incendiu electric în cabină"}, {"5725dc1638643c19005ace04": " izbucnit un incendiu electric în cabină"}, {"5725dc1638643c19005ace05": " înaltă presiune,"}, {"5725f39638643c19005acef7": " Nafzger"}, {"5725f39638643c19005acef8": " fără a se distruge legitimitatea istorică."}, {"5725f39638643c19005acef9": " înregistrări cu cinescop"}, {"5725f39638643c19005acefa": " Lowry Digital"}, {"5725f39638643c19005acefb": " nu a inclus îmbunătățiri ale calității sunetului."}, {"5725cc38ec44d21400f3d5bb": " cu reguli comune pentru cărbune și oțel"}, {"5725cc38ec44d21400f3d5bc": " Tratatul de la Roma din 1957 și Tratatul de la Maastricht din 1992"}, {"5725cc38ec44d21400f3d5bd": " 1985,"}, {"5725cc38ec44d21400f3d5be": " Norvegia până la urmă nu a aderat),"}, {"5725cc38ec44d21400f3d5bf": " Groenlanda"}, {"57268e2bf1498d1400e8e3b0": " energia atomică,"}, {"57268e2bf1498d1400e8e3b1": " 1992"}, {"57268e2bf1498d1400e8e3b2": " 1986,"}, {"57268e2bf1498d1400e8e3b3": " 1972"}, {"57268e2bf1498d1400e8e3b4": " 1985"}, {"572651f9f1498d1400e8dbee": " Parlamentul European și Consiliul Uniunii Europene"}, {"572651f9f1498d1400e8dbef": " iniția legi împotriva dorințelor Comisiei,"}, {"572651f9f1498d1400e8dbf0": " o dată la cinci ani,"}, {"572651f9f1498d1400e8dbf1": " două treimi"}, {"572651f9f1498d1400e8dbf2": " Comisie și Consiliu,"}, {"5726938af1498d1400e8e446": " Comisia"}, {"5726938af1498d1400e8e447": " Parlamentul European și Consiliul Uniunii Europene"}, {"5726938af1498d1400e8e448": " 1979,"}, {"5726938af1498d1400e8e449": " o dată la cinci ani,"}, {"5726938af1498d1400e8e44a": " Partidul Popular European"}, {"57265e455951b619008f70bb": " legea UE"}, {"57265e455951b619008f70bc": " protest împotriva naționalizării companiilor energetice din Italia."}, {"57265e455951b619008f70bd": " 1964 și 1968."}, {"5726975c708984140094cb1f": " Înaltele Curți Naționale"}, {"5726975c708984140094cb20": " 1964,"}, {"5726975c708984140094cb21": " Curtea de Justiție"}, {"5726a299dd62a815002e8b9e": "Niciuna"}, {"5726a299dd62a815002e8b9f": " statele membre"}, {"5726a299dd62a815002e8ba0": " 1950"}, {"5726a299dd62a815002e8ba1": " Curții Europene a Drepturilor Omului."}, {"5726a299dd62a815002e8ba2": " 1999,"}, {"5726a5525951b619008f78dd": " alegerii Partidului Laburist din Regatul Unit la guvernare"}, {"5726a5525951b619008f78de": " 1997,"}, {"5726a5525951b619008f78df": " Directiva Comitetului de Întreprindere"}, {"5726a5525951b619008f78e0": " 1996."}, {"5726a5525951b619008f78e1": " consultarea forței de muncă în întreprinderi"}, {"5725b81b271a42140099d097": " Amazonia sau Jungla Amazoniană,"}, {"5725b81b271a42140099d098": " 5.500.000"}, {"5725b81b271a42140099d099": " nouă"}, {"5725b81b271a42140099d09a": " patru"}, {"5725b81b271a42140099d09b": " peste jumătate"}, {"5728349dff5b5019007d9efe": " Amazoneregenwoud),"}, {"5728349dff5b5019007d9eff": "Pădurea Amazoniană"}, {"5728349dff5b5019007d9f00": " Brazilia,"}, {"5728349dff5b5019007d9f01": " peste jumătate"}, {"5728349dff5b5019007d9f02": " 16.000"}, {"5729e2316aef0514001550c4": " umedă"}, {"5729e2316aef0514001550c5": " 7.000.000"}, {"5729e2316aef0514001550c6": " nouă"}, {"5729e2316aef0514001550c7": " Brazilia,"}, {"5729e2316aef0514001550c8": " 16.000"}, {"5729feaf6aef051400155188": " 587.000"}, {"5729feaf6aef051400155189": " 587.000"}, {"5729feaf6aef05140015518a": " pășunat pentru șeptel."}, {"5729feaf6aef05140015518b": " cel de-al doilea"}, {"5729feaf6aef05140015518c": " 91%"}, {"572a005f1d046914007796b7": " fermierilor de soia."}, {"572a005f1d046914007796b8": " creșterea numărului de așezări și a defrișărilor."}, {"572a005f1d046914007796b9": " 8.646"}, {"572a005f1d046914007796bb": " reduse"}, {"572a005f1d046914007796ba": " 18%"}, {"572a020f6aef051400155198": " biodiversității"}, {"572a020f6aef051400155199": " distrugerea pădurii,"}, {"572a020f6aef05140015519a": " carbonului"}, {"572a020f6aef05140015519b": " 10%"}, {"572a020f6aef05140015519c": " 1,1 × 1011"}, {"572a0bebaf94a219006aa76f": " 2010,"}, {"572a0bebaf94a219006aa770": " 1.160.000"}, {"572a0bebaf94a219006aa771": " trei"}, {"572a0bebaf94a219006aa772": " 2005"}, {"572a0bebaf94a219006aa773": " 1,5 giga tone"}, {"5725bae289a1e219009abd90": " zece ori mai mult"}, {"5725bae289a1e219009abd91": " 100–150"}, {"5725bae289a1e219009abd92": " 25"}, {"5725c337271a42140099d163": " 100–150"}, {"5725c337271a42140099d164": " tentilla"}, {"5725c337271a42140099d165": " zece ori mai mult"}, {"5725c337271a42140099d166": " tentacule"}, {"5725c337271a42140099d167": " gurilor lor imense"}, {"5726400589a1e219009ac5ee": " zece ori mai mult"}, {"5726400589a1e219009ac5ef": " tentilla"}, {"5726400589a1e219009ac5f0": " gurilor lor imense"}, {"5726400589a1e219009ac5f1": " coloblaste,"}, {"5726400589a1e219009ac5f2": " 100–150 specii"}, {"5725c91e38643c19005acceb": " 66 de milioane de ani."}, {"5725c91e38643c19005accec": " monofiletice,"}, {"5725c91e38643c19005acced": " aproximativ 515 milioane de ani."}, {"5725c91e38643c19005accee": " tentacule"}, {"5726449f1125e71900ae1928": " aproximativ 515 milioane de ani."}, {"5726449f1125e71900ae1929": " extincția din Cretacic-Paleogen,"}, {"5726449f1125e71900ae192a": " monofiletice,"}, {"5726449f1125e71900ae192b": " tentacule"}, {"572648e8dd62a815002e8076": " cili"}, {"572648e8dd62a815002e8077": " principalul lor mijloc de deplasare."}, {"572648e8dd62a815002e8078": " ctene"}, {"572648e8dd62a815002e8079": " purtător de piepteni"}, {"57268da7f1498d1400e8e39c": " corpurilor lor moi, gelatinoase,"}, {"57268da7f1498d1400e8e39d": " meduză pieptene."}, {"57268da7f1498d1400e8e39e": " perioada de mijloc a Cambrianului."}, {"57268da7f1498d1400e8e39f": " trei"}, {"57268da7f1498d1400e8e3a0": " o gură mare,"}, {"57269016708984140094ca41": " bilaterilor,"}, {"57269016708984140094ca42": " Porifera"}, {"5725edfe38643c19005ace9f": " Sud-Vestul Fresno"}, {"5725edfe38643c19005acea0": " vest și sud."}, {"5725edfe38643c19005acea1": " afro-americane"}, {"5725edfe38643c19005acea2": " Hmong sau Laos)"}, {"5725edfe38643c19005acea3": " Sud-Vestul Fresno"}, {"5725f00938643c19005aced7": " M. Theo Kearney"}, {"5725f00938643c19005aced8": " palmieri"}, {"5725f00938643c19005aced9": " Strada Fresno și Bulevardul Thorne"}, {"5725f00938643c19005aceda": " Brookhaven,"}, {"5725f00938643c19005acedb": " Zonei de Vest,"}, {"5725f8f5ec44d21400f3d7b1": " 68.511"}, {"5725f8f5ec44d21400f3d7b2": " 11.698 (7,4%)"}, {"5725f8f5ec44d21400f3d7b3": " 1.388"}, {"5725f8f5ec44d21400f3d7b4": " 3,62."}, {"5725f8f5ec44d21400f3d7b5": " 3,07."}, {"5725fcbe271a42140099d3ad": " Secundară 99,"}, {"5725fcbe271a42140099d3ae": " Autostrada Sierra,"}, {"5725fcbe271a42140099d3af": " Secundară 41"}, {"5725fcbe271a42140099d3b0": " vest"}, {"5725fe63ec44d21400f3d7dd": "Fresno"}, {"5725fe63ec44d21400f3d7de": " 1950,"}, {"5725fe63ec44d21400f3d7df": " Secundară 99."}, {"5725fe63ec44d21400f3d7e0": " creșterii rapide a populației"}, {"5726385e271a42140099d797": " informații complete de adresare."}, {"5726385e271a42140099d798": " individual,"}, {"5726385e271a42140099d799": " o adresă de destinație, adresă sursă,"}, {"5726385e271a42140099d79a": " se elimină nevoia unei căi dedicate"}, {"57263c78ec44d21400f3dc7b": " 1969."}, {"57263c78ec44d21400f3dc7c": " Două diferențe fundamentale"}, {"57263c78ec44d21400f3dc7d": " o livrare secvențială a informației la gazdă."}, {"57263c78ec44d21400f3dc7e": " Colecția de protocoale"}, {"57263ea0271a42140099d7c3": " o colecție de protocoale de rețea"}, {"57263ea0271a42140099d7c4": " pentru a conecta două mini computere PDP-11."}, {"57263ea0271a42140099d7c5": " șapte"}, {"57263ea0271a42140099d7c6": " standarde deschise cu specificații publicate,"}, {"5726414e271a42140099d7e5": " cu scopul de a contribui la dezvoltarea educațională și economică a statului."}, {"5726414e271a42140099d7e6": " conexiuni la calculatorul cu mare putere de calcul CDC"}, {"5726414e271a42140099d7e7": " TCP/IP"}, {"5726472bdd62a815002e8042": " un consorțiu de rețele de calculatoare,"}, {"5726472bdd62a815002e8043": " Quest,"}, {"5726472bdd62a815002e8044": " Abilene"}, {"5726472bdd62a815002e8045": " Quest,"}, {"5726472bdd62a815002e8046": " Rețeaua Internet2."}, {"57264b3edd62a815002e80aa": " Regele Franței"}, {"57264b3edd62a815002e80ab": " Regele Franței"}, {"57264b3edd62a815002e80ac": " Miasma."}, {"57264b3edd62a815002e80ad": " teoria Miasma."}, {"57264f18f1498d1400e8dbae": " (ramuri genetice)"}, {"57264f18f1498d1400e8dbaf": " Y. p. orientalis și Y. p. medievalis,"}, {"57264f18f1498d1400e8dbb0": " ciuma este posibil să fi intrat în Europa în două valuri."}, {"57264f18f1498d1400e8dbb1": " lunii noiembrie 1347"}, {"57264f18f1498d1400e8dbb2": " primăvara anului 1349,"}, {"5726534d708984140094c26d": " că aceasta ar avea la bază o formă de antrax,"}, {"5726534d708984140094c26e": " o combinație de antrax și alte pandemii."}, {"5726534d708984140094c26f": " tifosul, variola și infecțiile respiratorii."}, {"5726534d708984140094c270": " „otrăvire a sângelui”)"}, {"5726534d708984140094c271": " 25"}, {"57265642f1498d1400e8dc68": " aproximativ 40.000"}, {"57265642f1498d1400e8dc69": " Rusia,"}, {"57265642f1498d1400e8dc6b": " Ciuma"}, {"57265642f1498d1400e8dc6c": " 1654."}, {"57265642f1498d1400e8dc6a": " 22 de ori,"}, {"5726577f708984140094c301": " 1500 și 1850."}, {"5726577f708984140094c302": " 30 și 50 de mii"}, {"5726577f708984140094c303": " până în al doilea sfert al secolului 19."}, {"5726577f708984140094c304": " două treimi"}, {"572663a9f1498d1400e8ddf2": " cea mai recentă eră,"}, {"572663a9f1498d1400e8ddf4": " Cuaternarul"}, {"572663a9f1498d1400e8ddf5": " Epoca pleistocenă"}, {"572663a9f1498d1400e8ddf6": " perioada cuaternară."}, {"572669a9dd62a815002e8416": "Principiul succesiunii faunelor"}, {"572669a9dd62a815002e8417": " apariția fosilelor în rocile sedimentare."}, {"572669a9dd62a815002e8418": " complex,"}, {"572669a9dd62a815002e8419": " absența"}, {"572669a9dd62a815002e841a": " Charles Darwin,"}, {"57268066708984140094c821": " stratigrafii"}, {"57268066708984140094c822": " geofizice"}, {"57268066708984140094c823": " registrele sondelor forate"}, {"57268066708984140094c824": " programe de calculator"}, {"57268066708984140094c825": " apă, cărbune și hidrocarburi."}, {"572683f95951b619008f7525": " Persia,"}, {"572683f95951b619008f7526": " Abu al-Rayhan al-Biruni"}, {"572683f95951b619008f7527": " Shen Kuo"}, {"572683f95951b619008f7528": " Ibn Sina"}, {"572683f95951b619008f7529": " depunerea de aluviuni."}, {"57268527708984140094c8bf": "James Hutton"}, {"57268527708984140094c8c0": " Teoria Pământului"}, {"57268527708984140094c8c1": " 1795"}, {"57268527708984140094c8c2": " Teoria Pământului"}, {"5726660d5951b619008f71b1": " Pons Aelius,"}, {"5726660d5951b619008f71b2": " Râul Tyne."}, {"5726660d5951b619008f71b3": " 2000 de oameni."}, {"5726660d5951b619008f71b4": " Zidul lui Hadrian"}, {"5726660d5951b619008f71b5": " Pictish"}, {"572671e55951b619008f72d7": " Piața Măcelarului."}, {"572671e55951b619008f72d8": " 1835"}, {"572671e55951b619008f72d9": " 2000"}, {"572671e55951b619008f72da": " tablou"}, {"572671e55951b619008f72db": " English Heritage."}, {"5726847f708984140094c8ab": " folk rock"}, {"5726847f708984140094c8ac": " (1971),"}, {"5726847f708984140094c8ad": " Venom,"}, {"5726847f708984140094c8ae": " Skyclad,"}, {"5726847f708984140094c8af": " Duran Duran"}, {"57268a8fdd62a815002e88ce": " The Tyne and Wear Metro,"}, {"57268a8fdd62a815002e88cf": " cinci"}, {"57268a8fdd62a815002e88d0": " un nivel profund"}, {"57268a8fdd62a815002e88d1": " un pod peste Tyne, între Newcastle și Gateshead,"}, {"57268a8fdd62a815002e88d2": " peste 37 de milioane"}, {"57269698dd62a815002e8a6c": " două"}, {"57269698dd62a815002e8a6d": " Universitatea Newcastle"}, {"57269698dd62a815002e8a6e": " titlul râvnit de Universitatea Anului"}, {"57269698dd62a815002e8a6f": " Politehnica s-a transformat în universități noi."}, {"57269698dd62a815002e8a70": " Universitatea Northumbria"}, {"572685cd5951b619008f7573": " Marea Expoziție"}, {"572685cd5951b619008f7574": " Henry Cole,"}, {"572685cd5951b619008f7575": " Muzeul Producătorilor,"}, {"572685cd5951b619008f7576": " Casa Somerset."}, {"572685cd5951b619008f7577": " Gottfried Semper"}, {"5726bf325951b619008f7cfd": " 70.000"}, {"5726bf325951b619008f7cfe": " China, Japonia și Coreea."}, {"5726bf325951b619008f7cff": " Galeria T. T. Tsui"}, {"5726bf325951b619008f7d00": " 1991,"}, {"5726bf325951b619008f7d01": " Ming și Qing,"}, {"5726e37ef1498d1400e8eed8": " 14.000"}, {"5726e37ef1498d1400e8eed9": " Lume și Imagini."}, {"5726e37ef1498d1400e8eeda": " nu a supraviețuit îmbrăcămintea de zi cu zi"}, {"5726e37ef1498d1400e8eedb": " 1913,"}, {"5726e37ef1498d1400e8eedc": " Harrods"}, {"5726f1ec708984140094d6aa": " 5100"}, {"5726f1ec708984140094d6ad": " Bryan Davies"}, {"5726f1ec708984140094d6ab": " Muzeul Horniman"}, {"5726f1ec708984140094d6ac": " 35"}, {"5726f1ec708984140094d6a9": " 2020,"}, {"5726f4a0708984140094d6e9": " 1857"}, {"5726f4a0708984140094d6ea": " 233"}, {"5726f4a0708984140094d6eb": " o,Galerie Națională de Artă Britanică’,"}, {"5726f4a0708984140094d6ec": " The Hay Wain"}, {"5726f4a0708984140094d6ed": " britanici"}, {"572734af708984140094dae3": " sigla circulară numită și punctul,"}, {"572734af708984140094dae4": " Troika Design Group"}, {"572734af708984140094dae5": " negru și galben"}, {"572734af708984140094dae6": " punctul,"}, {"572735a15951b619008f86bf": " Pittard Sullivan,"}, {"572735a15951b619008f86c0": " 2015,"}, {"572735a15951b619008f86c1": " „We Love TV”"}, {"572735a15951b619008f86c2": " buletinele personalizate de reclame și ale companiei de producție,"}, {"57273f9d708984140094db51": " Robert Kintner"}, {"57273f9d708984140094db52": " Rețeaua de Televiziune Dumont,"}, {"57273f9d708984140094db53": " „ABC-DuMont”,"}, {"57273f9d708984140094db54": " 5 milioane de dolari"}, {"572743fb708984140094db93": " 1970,"}, {"572743fb708984140094db94": " CBS și NBM"}, {"572743fb708984140094db95": " comportamentale și demografice"}, {"57276166dd62a815002e9bd8": " 90%"}, {"57276166dd62a815002e9bd9": " Dynasty"}, {"57276166dd62a815002e9bda": " Mork & Mindy."}, {"57276166dd62a815002e9bdb": " Nickelodeon."}, {"5726a8d4dd62a815002e8c34": " Onggirat,"}, {"5726a8d4dd62a815002e8c35": " Merkit"}, {"5726a8d4dd62a815002e8c36": " Jamukha,"}, {"5726a8d4dd62a815002e8c37": " Jochi"}, {"5726a8d4dd62a815002e8c38": " (1185 –1226),"}, {"5726acc1f1498d1400e8e6ca": " aristocrația tradițională mongolă,"}, {"5726acc1f1498d1400e8e6cb": " Kokochu"}, {"5726acc1f1498d1400e8e6cc": " 1186,"}, {"5726acc1f1498d1400e8e6cd": " Bătălia de la Dalan Balzhut."}, {"5726acc1f1498d1400e8e6ce": " Qara Khitai."}, {"57273455f1498d1400e8f48c": " Edsen Khoroo)"}, {"57273455f1498d1400e8f48d": " Dongshan Dafo Dian,"}, {"57273455f1498d1400e8f48e": " Mănăstirea Kumbum sau Ta'er Shi de lângă Xining,"}, {"57273455f1498d1400e8f48f": " La începutul anului 1954,"}, {"57273455f1498d1400e8f490": " Gărzile Roșii"}, {"57273dccdd62a815002e99fa": " Marea Caspică"}, {"57273dccdd62a815002e99fb": " Marea Caspică"}, {"57273dccdd62a815002e99fc": " Ögedei Han,"}, {"57273dccdd62a815002e99fd": " 1279,"}, {"572754cd5951b619008f8863": " Hulagu Khan,"}, {"572754cd5951b619008f8864": " Ghazan Han,"}, {"572754cd5951b619008f8865": " Ghazan Han,"}, {"572754cd5951b619008f8866": " 1237"}, {"572754cd5951b619008f8867": " Novgorod și Pskov."}, {"5726da89dd62a815002e92b2": " alți tehnicieni de farmacie principali."}, {"5726da89dd62a815002e92b3": " Consiliului Farmaceutic General."}, {"5726da89dd62a815002e92b4": " farmacist și tehnician de farmacie."}, {"5726da89dd62a815002e92b5": " Consiliului Farmaceutic General."}, {"5726da89dd62a815002e92b6": " gestionare a departamentului farmaceutic și a zonelor de specialitate"}, {"5726ddf6f1498d1400e8ee04": " botanică și chimie"}, {"5726ddf6f1498d1400e8ee05": " Muhammad ibn Zakarīya Rāzi"}, {"5726ddf6f1498d1400e8ee06": " Abu al-Qasim al-Zahrawi"}, {"5726ddf6f1498d1400e8ee08": " Avicenna"}, {"5726ddf6f1498d1400e8ee07": " carbonatul de sodiu și carbonatul de potasiu"}, {"5726e08e5951b619008f810f": " legislației farmaceutice"}, {"5726e08e5951b619008f8110": " rețetele pacienților și siguranța pacientului."}, {"5726e08e5951b619008f8111": " automatizare,"}, {"5726e08e5951b619008f8112": " rețetele pacienților și siguranța pacientului."}, {"5726e08e5951b619008f8113": " cerințe referitoare la condiții de depozitare,"}, {"5726ea985951b619008f8261": " revizii ale regimului de medicamente"}, {"5726ea985951b619008f8262": " aziluri pentru bătrâni,"}, {"5726ea985951b619008f8263": " Omnicare, Kindred Healthcare și PharMerica)."}, {"5726ea985951b619008f8264": " mulți bătrâni iau acum numeroase medicamente,"}, {"5726ea985951b619008f8265": " angajează farmaciști consultanți"}, {"5726f48df1498d1400e8f0da": " separat de cea de medic."}, {"5726f48df1498d1400e8f0db": " farmaciștii"}, {"5726f48df1498d1400e8f0dc": " Codul de Etică al Asociației Medicale Americane"}, {"5726f48df1498d1400e8f0dd": " 7 până la 10"}, {"5726f48df1498d1400e8f0de": " plăți sub formă de „mită”."}, {"5726eb8bf1498d1400e8efe2": " boli autoimune, boli inflamatorii și cancer."}, {"5726eb8bf1498d1400e8efe3": " atunci când sistemul imunitar este mai puțin activ decât normal,"}, {"5726eb8bf1498d1400e8efe4": " infecții recurente, amenințătoare de viață."}, {"5726eb8bf1498d1400e8efe5": " imunodeficiența severă combinată,"}, {"5726eb8bf1498d1400e8efe6": " tiroida Hashimoto,"}, {"5728f2e26aef051400154896": " Imunodeficiența"}, {"5728f2e26aef051400154897": " autoimunitatea"}, {"5728f2e26aef051400154898": " Imunologia"}, {"5728f2e26aef051400154899": " HIV/SIDA"}, {"572a03086aef0514001551a2": " Glucocorticoizii"}, {"572a03086aef0514001551a3": " citotoxice sau imunosupresive,"}, {"572a03086aef0514001551a4": " metotrexatul sau azatioprina."}, {"572a03086aef0514001551a5": " ciclosporina,"}, {"572a04d51d046914007796cd": " celulele citotoxice Natural Killer și CTLs"}, {"572a04d51d046914007796ce": " cortizolul și catecolaminele"}, {"572a04d51d046914007796cf": " melatoninei."}, {"572a04d51d046914007796d0": " radicali liberi"}, {"572a07fc6aef0514001551dc": " imunoglobulinele și receptorii de celule T)"}, {"572a07fc6aef0514001551dd": " chișcarul și mixina."}, {"572a07fc6aef0514001551de": " limfocitari variabili"}, {"572a07fc6aef0514001551df": " adaptiv"}, {"572a0e4b6aef051400155214": " ascunși."}, {"572a0e4b6aef051400155215": " HIV,"}, {"572a0e4b6aef051400155216": " Trypanosoma brucei"}, {"572a0e4b6aef051400155217": " antigenelor"}, {"5727213c708984140094da35": " Percy Shelley"}, {"5727213c708984140094da36": " nonviolent."}, {"5727213c708984140094da38": " Satyagraha"}, {"5727213c708984140094da39": " campaniei sale pentru o India liberă."}, {"5727213c708984140094da37": " Henry David Thoreau"}, {"5728d63c4b864d1900164f18": " Percy Shelley"}, {"5728d63c4b864d1900164f19": " o India liberă."}, {"5728d63c4b864d1900164f1a": " nonviolent."}, {"5728d63c4b864d1900164f1c": " Masca Anarhiei"}, {"5728d63c4b864d1900164f1b": " Gandhi"}, {"5728202c4b864d19001644ec": " Nesupunerea civilă revoluționară"}, {"5728202c4b864d19001644ed": " maghiarii"}, {"5728202c4b864d19001644ee": " Ferenc Deák"}, {"5728202c4b864d19001644ef": " Gandhi"}, {"5728202c4b864d19001644f0": " o altă chestiune."}, {"5728e07e3acd2414000e00e9": " nerespectare a legilor"}, {"5728e07e3acd2414000e00ea": " de a face ca anumite legi să devină ineficiente,"}, {"5728e07e3acd2414000e00eb": " „schimbarea sau desființarea” unui guvern nedrept,"}, {"5728e07e3acd2414000e00ec": " o tentativă activă de a răsturna un guvern"}, {"5728e07e3acd2414000e00ed": " Gandhi"}, {"57282dfb4b864d1900164668": " funcționarea unui sistem."}, {"57282dfb4b864d1900164669": " blocarea porților cu lacăte și folosirea secerelor"}, {"57282dfb4b864d190016466a": " blocarea porților cu lacăte și folosirea secerelor"}, {"57282dfb4b864d190016466b": " coerciție limitată"}, {"57282dfb4b864d190016466c": " coercitive."}, {"5728e715ff5b5019007da914": " coercitive."}, {"5728e715ff5b5019007da916": " îngreunează funcționarea unui sistem."}, {"5728e715ff5b5019007da917": " angaja într-un dialog moral,"}, {"5728e715ff5b5019007da918": " coercitive."}, {"5728eb1a3acd2414000e01c5": " pedeapsa"}, {"5728eb1a3acd2414000e01c6": " încălcarea dreptului penal care nu încalcă drepturile celorlalți."}, {"5728eb1a3acd2414000e01c7": " anarhiștii,"}, {"5728eb1a3acd2414000e01c8": " anarhiștii,"}, {"5728eb1a3acd2414000e01c9": " încălcarea dreptului penal"}, {"5728eef92ca10214002daab0": " negocierea pedepsei,"}, {"5728eef92ca10214002daab1": " acuzarea"}, {"5728eef92ca10214002daab2": " tactici de solidaritate"}, {"5728eef92ca10214002daab3": " negocierea pedepsei,"}, {"5728eef92ca10214002daab4": " Mohandas Gandhi"}, {"57273a465951b619008f86ff": "Construirea"}, {"57273a465951b619008f8700": " confecționarea"}, {"57273a465951b619008f8701": " șase până la nouă"}, {"57273a465951b619008f8702": " proiectare și finanțare"}, {"57273a465951b619008f8703": " un client cunoscut."}, {"57273e50dd62a815002e9a02": " o revistă de comerț pentru industria construcțiilor."}, {"57273e50dd62a815002e9a03": " ENR"}, {"57273e50dd62a815002e9a04": " 2014,"}, {"57273e50dd62a815002e9a05": " transportul, canalizarea, deșeurile periculoase și apa"}, {"57273f27dd62a815002e9a0a": " construirea de clădiri, construcții civile și industriale,"}, {"57273f27dd62a815002e9a0b": " firmele care prestează servicii în domeniul construcțiilor"}, {"57273f27dd62a815002e9a0c": "Clasificarea Standard a Industriei"}, {"57273f27dd62a815002e9a0d": " (firme care gestionează proiecte de construcții"}, {"57274e0d708984140094dbe5": " specialităților"}, {"57274e0d708984140094dbe6": " companii complet diferite,"}, {"57274e0d708984140094dbe7": " „aprovizionare universală”"}, {"57274e0d708984140094dbe8": " „proiectare-execuție”,"}, {"572750e8dd62a815002e9af0": " codul zonal și de construire."}, {"572750e8dd62a815002e9af1": " proprietarului."}, {"572750e8dd62a815002e9af2": " dorința de a preveni lucrurile care sunt incontestabil rele"}, {"572750e8dd62a815002e9af3": " lucruri care reprezintă o chestiune de obișnuință sau așteptări,"}, {"572750e8dd62a815002e9af4": " Un avocat"}, {"57274b35f1498d1400e8f5d4": "Ergänzungsschulen"}, {"57274b35f1498d1400e8f5d5": " școli profesionale."}, {"57274b35f1498d1400e8f5d6": " taxele de școlarizare aplicate studenților acestora."}, {"57274b35f1498d1400e8f5d7": " religioase"}, {"57274beff1498d1400e8f5e4": " școală independentă care nu beneficiază de ajutor."}, {"57274beff1498d1400e8f5e5": " CBSE"}, {"57274beff1498d1400e8f5e6": " 30"}, {"57274beff1498d1400e8f5e7": " guvernul uniunii"}, {"5727515f708984140094dc11": " Legea școlilor"}, {"5727515f708984140094dc12": " 1996"}, {"5727515f708984140094dc13": " „independente”"}, {"5727515f708984140094dc14": " școlile private tradiționale"}, {"5727515f708984140094dc15": " nouăsprezece."}, {"57275409708984140094dc35": " școlile guvernamentale rezervate anterior copiilor albi."}, {"57275409708984140094dc36": " mai bune"}, {"57275409708984140094dc37": " mult mai mari"}, {"572757bef1498d1400e8f690": " Brown vs. Consiliul de Educație al Topeka,"}, {"572757bef1498d1400e8f691": " private."}, {"572757bef1498d1400e8f692": " sudul"}, {"572757bef1498d1400e8f693": " albi"}, {"572757bef1498d1400e8f694": " afro-americani"}, {"5727aec03acd2414000de991": " Boston:"}, {"5727aec03acd2414000de992": " 37,6 miliarde de dolari"}, {"5727aec03acd2414000de993": " Charles"}, {"5727aec03acd2414000de994": " unsprezece"}, {"5727aec03acd2414000de995": " Harvard Yard"}, {"5727cc15ff5b5019007d9576": " campusul de 358 de acri (145 ha)"}, {"5727cc15ff5b5019007d9577": " Podul John W. Weeks"}, {"5727cc15ff5b5019007d9578": " campusul de 21 de acri (8,5 ha)"}, {"5727d0f73acd2414000ded13": " sfârșitul anilor 1980,"}, {"5727d0f73acd2414000ded14": " Ducele Kent-Brown."}, {"5727d0f73acd2414000ded15": " 230 milioane $"}, {"5727d1c93acd2414000ded3f": " 5,3 %"}, {"5727d1c93acd2414000ded40": " 2007,"}, {"5727d1c93acd2414000ded41": " programul se credea că dezavantajează candidații cu venituri reduse"}, {"5727d1c93acd2414000ded42": " 2016"}, {"5727de862ca10214002d9860": " Ban Ki-moon"}, {"5727de862ca10214002d9861": " Juan Manuel Santos"}, {"5727de862ca10214002d9862": " José María Figueres"}, {"5727de862ca10214002d9863": " Fan S. Noli;"}, {"5727c94bff5b5019007d954a": "Jacksonville"}, {"5727c94bff5b5019007d954b": " 1.345.596"}, {"5727c94bff5b5019007d954c": " 12-lea"}, {"5727c94bff5b5019007d954d": " Districtului Duval,"}, {"5727c94bff5b5019007d954e": " 1968."}, {"5727cb4b2ca10214002d9676": " St. Johns,"}, {"5727cb4b2ca10214002d9677": " 340 de mile"}, {"5727cb4b2ca10214002d9678": " Fort Caroline,"}, {"5727cb4b2ca10214002d9679": " tribul Timucua,"}, {"5727cb4b2ca10214002d967a": " Andrew Jackson,"}, {"57280fd3ff5b5019007d9c26": " râul St. John"}, {"57280fd3ff5b5019007d9c27": " Franța."}, {"57280fd3ff5b5019007d9c28": " Pedro Menéndez de Avilés"}, {"57280fd3ff5b5019007d9c29": " San Mateo,"}, {"57280fd3ff5b5019007d9c2a": " Fortului Caroline"}, {"57281ab63acd2414000df493": " Construirea autostrăzilor"}, {"57281ab63acd2414000df494": " 55,1%"}, {"57281ab63acd2414000df495": " „exod al albilor”"}, {"57281ab63acd2414000df496": " W. Haydon Burns"}, {"57281ab63acd2414000df497": " Doilea Război Mondial."}, {"572824f13acd2414000df58f": " Uraganul Dora"}, {"572824f13acd2414000df590": " 110 mile/h"}, {"572824f13acd2414000df591": " Furtuna Tropicală Berly,"}, {"572824f13acd2414000df592": " Categoria 2"}, {"572824f13acd2414000df593": " 2008"}, {"572a1046af94a219006aa78d": " dovezi"}, {"572a1046af94a219006aa78e": " limitarea cererii agregate."}, {"572a1046af94a219006aa78f": " Economistul"}, {"572a1046af94a219006aa790": " importanța în creștere a capitalului uman în dezvoltare."}, {"572a1046af94a219006aa791": " educarea la scara largă"}, {"572a11663f37b31900478693": " 1993"}, {"572a11663f37b31900478694": " dăunător,"}, {"572a11663f37b31900478695": " canalele prin care inegalitatea poate afecta creșterea economică."}, {"572a11663f37b31900478696": " taxare redistributivă,"}, {"572a11663f37b31900478697": " instabile politic și social,"}, {"572a13841d0469140077973b": " ipoteza curbei Kuznets,"}, {"572a13841d0469140077973c": " descrește."}, {"572a13841d0469140077973d": " Thomas Piketty"}, {"572a13841d0469140077973e": " Economistul"}, {"572a13841d0469140077973f": " războaiele și „șocurile economice și politice puternice”"}, {"572a18a4af94a219006aa7df": " anii 1970"}, {"572a18a4af94a219006aa7e0": " cererea redusă a consumatorilor."}, {"572a18a4af94a219006aa7e1": " inegalitatea crescută a veniturilor."}, {"572a18a4af94a219006aa7e2": " șapte ani"}, {"572a18a4af94a219006aa7e3": " egalitate în distribuția venitului.”"}, {"572a1a5c6aef051400155284": " eforturi speciale"}, {"572a1a5c6aef051400155285": " nivelul existent al inegalității."}, {"572a1a5c6aef051400155286": " același grad de reducere."}, {"572a1a5c6aef051400155287": " Națiunilor Unite"}, {"572a1a5c6aef051400155288": " reducerea sărăciei.”"}, {"5727f3193acd2414000df0a5": " rareori"}, {"5727f3193acd2414000df0a6": " Maistru,"}, {"5727f3193acd2414000df0a7": " capacitatea de regenerare"}, {"5727f3193acd2414000df0a8": " unul sau mai mulți însoțitori."}, {"5727f3193acd2414000df0a9": " Lord al Timpului,"}, {"57280f0d3acd2414000df35b": " An Unearthly Child"}, {"57280f0d3acd2414000df35c": " Susan Foreman."}, {"57280f0d3acd2414000df35d": " 2005"}, {"57280f0d3acd2414000df35e": " distrusă"}, {"57280f0d3acd2414000df35f": " „Smith and Jones” (Smith și Jones) (2007),"}, {"572811434b864d190016438c": " feminin,"}, {"572811434b864d190016438d": " Jack Harkness (John Barrowman)"}, {"572811434b864d190016438e": " Cel de-al Unsprezecelea Doctor"}, {"572811434b864d190016438f": " Pearl Mackie"}, {"572811434b864d1900164390": " (Catherine Tate)"}, {"57281a952ca10214002d9dea": " Dudley Simpson,"}, {"57281a952ca10214002d9deb": " Planet of Giants"}, {"57281a952ca10214002d9dec": " primii 15 ani"}, {"57281a952ca10214002d9ded": " The Horns of Nimon"}, {"57281a952ca10214002d9dee": " The Talons of Weng-Chiang"}, {"572828383acd2414000df5c3": " Trevor Martin"}, {"572828383acd2414000df5c4": " Doctor Who – The Ultimate Adventure"}, {"572828383acd2414000df5c5": " The Curse of the Daleks"}, {"572828383acd2414000df5c6": " Doctor Who – The Ultimate Adventure"}, {"572828383acd2414000df5c7": " David Banks"}, {"57284b904b864d19001648e2": " Patrulaterele Principale,"}, {"57284b904b864d19001648e3": " șase"}, {"57284b904b864d19001648e4": " Cobb, Shepley, Rutan și Coolidge,"}, {"57284b904b864d19001648e5": " Turnul Magdalen"}, {"57284b904b864d19001648e6": " Sălii Christ Church)."}, {"57284d484b864d1900164900": " anii 1940,"}, {"57284d484b864d1900164901": " Eero Saarinen"}, {"57284d484b864d1900164902": " școala de Administrare a Serviciilor Sociale a universității;"}, {"57284d484b864d1900164903": " Harris"}, {"57284d484b864d1900164904": " (2003),"}, {"572855973acd2414000df925": " Laborator"}, {"572855973acd2414000df926": " școala Ortogenică Sonia Shankman"}, {"572855973acd2414000df927": " patru"}, {"572855973acd2414000df928": " școli publice semi-autonome"}, {"572855973acd2414000df929": " campusul Universității din Chicago."}, {"57286951ff5b5019007da20e": " Satya Nadella,"}, {"57286951ff5b5019007da20f": " Satya Nadella,"}, {"57286951ff5b5019007da210": " Larry Ellison,"}, {"57286951ff5b5019007da211": " Larry Ellison,"}, {"57286951ff5b5019007da212": " Jon Corzine,"}, {"572870b2ff5b5019007da222": " Thomas Sowell,"}, {"572870b2ff5b5019007da223": " Thomas Sowell,"}, {"572870b2ff5b5019007da224": " Paul Samuelson,"}, {"572870b2ff5b5019007da225": " Eugene Fama,"}, {"57286dfa2ca10214002da332": " 1279."}, {"57286dfa2ca10214002da333": " unui taifun ostil."}, {"57286dfa2ca10214002da334": " Annam"}, {"57286dfa2ca10214002da335": " Bătălia de la Bạch Đặng"}, {"57286dfa2ca10214002da336": " Bătălia de la Bạch Đặng (1288)."}, {"57286fa83acd2414000df9e5": " Gegeen Han,"}, {"57286fa83acd2414000df9e6": " 1321 și 1323."}, {"57286fa83acd2414000df9e7": " Baiju."}, {"57286fa83acd2414000df9e8": " instituțiile comprehensive ale Marelui Yuan"}, {"57286fa83acd2414000df9e9": " cinci"}, {"57287d4a2ca10214002da3e4": " Han, Khitan, Jurchen, mongol,"}, {"57287d4a2ca10214002da3e5": " Tang, Song,"}, {"57287d4a2ca10214002da3e6": " Liu Bingzhong și Yao Shu"}, {"57287d4a2ca10214002da3e7": " tripartită"}, {"57287d4a2ca10214002da3e8": " Cenzoratul pentru supraveghere și inspecție internă."}, {"572881d34b864d1900164a5a": " angajați la două spitale imperiale"}, {"572881d34b864d1900164a5b": " Iisus Interpretul"}, {"572881d34b864d1900164a5c": " 1263,"}, {"572881d34b864d1900164a5d": " sistemul său umoral"}, {"572881d34b864d1900164a5e": " yin-yang și wuxing"}, {"5728848cff5b5019007da298": " Frederick W. Mote"}, {"5728848cff5b5019007da299": " „gradele de privilegii”"}, {"5728848cff5b5019007da29a": " trăiau în sărăcie"}, {"5728848cff5b5019007da29b": " trăiau în sărăcie"}, {"57290b21af94a219006a9fcf": " jos"}, {"57290b21af94a219006a9fd0": " 139"}, {"57290b21af94a219006a9fd1": " 139"}, {"57290b21af94a219006a9fd2": " Comisii de Etică și Anticorupție noi și independente."}, {"57290ee2af94a219006a9fff": " 28 februarie 2008,"}, {"57290ee2af94a219006aa000": " cel de-al doilea Prim Ministru al Kenyei."}, {"57290ee2af94a219006aa001": " tabăra PNU"}, {"57290ee2af94a219006aa002": " PNU cât și din cea a ODM,"}, {"57290ee2af94a219006aa003": " până la sfârșitul mandatului actual"}, {"572914f46aef051400154a46": " Președintele Statelor Unite Barack Obama a ales să nu viziteze țara"}, {"572914f46aef051400154a47": " Președintele Statelor Unite Barack Obama"}, {"572914f46aef051400154a48": " China"}, {"572914f46aef051400154a49": " iulie 2015,"}, {"572920d73f37b31900478055": " agricultură."}, {"572920d73f37b31900478056": " 30%"}, {"572920d73f37b31900478057": " 9 și 18 ani."}, {"572920d73f37b31900478058": " sărăcia,"}, {"5729281baf94a219006aa11f": " crichet, raliu, fotbal, rugby, și box."}, {"5729281baf94a219006aa120": " poziția sa dominantă la probele de atletism"}, {"5729281baf94a219006aa121": " Sportivii kenyeni"}, {"5729281baf94a219006aa122": " Maroc și Etiopia"}, {"57293bc91d0469140077919b": " Hoesung Lee"}, {"57293bc91d0469140077919c": " coreean"}, {"57293bc91d0469140077919d": " Ismail El Gizouli,"}, {"57293bc91d0469140077919e": " Hoesung Lee"}, {"57293bc91d0469140077919f": " februarie 2015."}, {"57293e221d046914007791d5": " emisiile care rezultă în urma activităților umane cresc semnificativ"}, {"57293e221d046914007791d6": " emisiile care rezultă în urma activităților umane"}, {"57293e221d046914007791d7": " mai mult de jumătate"}, {"57293e221d046914007791d8": " „business as usual”"}, {"57293e221d046914007791d9": " 0,3 până la 0,6 °C"}, {"572940973f37b319004781a5": " acea concluzie din rezumatul final a fost riguroasă."}, {"572940973f37b319004781a6": " „aplicarea deficitară"}, {"572940973f37b319004781a7": " WWF,"}, {"572940973f37b319004781a8": " WWF,"}, {"57294209af94a219006aa201": " 1999"}, {"57294209af94a219006aa202": " Michael E. Mann,"}, {"57294209af94a219006aa203": " graficul crosa de hochei ”."}, {"57294209af94a219006aa204": " Figura 2.21"}, {"57294e6b1d04691400779275": " Protocolul de la Montreal"}, {"57294e6b1d04691400779276": " schimbărilor climatice,"}, {"57294e6b1d04691400779277": " obiective diferite,"}, {"572957ad1d046914007792d9": " eucariotă"}, {"572957ad1d046914007792da": " aproximativ un milion de ani"}, {"572957ad1d046914007792db": " membrane lipidice dublu stratificate interioare"}, {"572957ad1d046914007792dc": " fagozomale"}, {"572957ad1d046914007792dd": " pierdute sau transferate în nucleul gazdei."}, {"5729582b1d046914007792e3": " cloroplast)."}, {"5729582b1d046914007792e4": " trei"}, {"5729582b1d046914007792e5": " cloroplastele primare"}, {"5729582b1d046914007792e6": " linia cloroplastelor verzi."}, {"5729582b1d046914007792e7": " linia cloroplastelor verzi"}, {"572968cf1d046914007793cb": " plastom."}, {"572968cf1d046914007793cc": " plastom."}, {"572968cf1d046914007793cd": " 1962"}, {"572968cf1d046914007793ce": " 1986"}, {"572968cf1d046914007793cf": " două echipe de cercetători japonezi"}, {"57296b151d046914007793f1": "Transferul endosimbiotic de gene"}, {"57296b151d046914007793f2": " existenței cloroplastului pierdut."}, {"57296b151d046914007793f3": " heterokontofit)"}, {"57296b151d046914007793f4": " chromalveolatelor."}, {"57296d1b1d0469140077940d": " descendenții"}, {"57296d1b1d0469140077940e": " acestea sunt descendenții cianobacteriilor endosimbiotice."}, {"57296d1b1d0469140077940f": " omoloage"}, {"57296d571d04691400779413": " 5"}, {"57296d571d04691400779414": " număr compus."}, {"57296d571d04691400779415": " Teorema fundamentală a aritmeticii"}, {"57296d571d04691400779416": " numere întregi,"}, {"57296d571d04691400779417": " 1"}, {"57296f293f37b319004783a3": " primalitate."}, {"57296f293f37b319004783a4": " diviziune de probă."}, {"57296f293f37b319004783a5": " Testul de primalitate Miller–Rabin,"}, {"57296f293f37b319004783a6": " Testul de primalitate Miller–Rabin,"}, {"57296f293f37b319004783a7": " 22.338.618"}, {"572991943f37b319004784a1": " Conjectura lui Polignac"}, {"572991943f37b319004784a2": " (n+1)"}, {"572991943f37b319004784a3": " Conjectura lui Polignac"}, {"572991943f37b319004784a4": " n2 + 1."}, {"572991943f37b319004784a5": " Conjectura lui Brocard"}, {"57299a6f6aef051400155016": " un caracter minimal sau indecompozabil,"}, {"57299a6f6aef051400155017": " mulțimea numerelor prime"}, {"57299a6f6aef051400155019": " sub forma unei sume conectate a unor noduri prime."}, {"57299a6f6aef05140015501a": " orice obiect se poate descompune,"}, {"57299a6f6aef051400155018": " „prim”"}, {"5729a26d6aef05140015505a": " devine mai mică"}, {"5729a26d6aef05140015505b": " înainte și înapoi la câmpurile completate"}, {"5729a26d6aef05140015505c": " valoarea absolută"}, {"5729a26d6aef05140015505d": " local-global"}, {"572f6a0ba23a5019007fc5eb": " Defileul Rinului,"}, {"572f6a0ba23a5019007fc5ec": " Defileul Rinului,"}, {"572f6a0ba23a5019007fc5ed": " prin eroziune."}, {"572f6a0ba23a5019007fc5ee": " „Rinul romantic”,"}, {"572ff12e04bcaa1900d76eff": " Defileul Rinului,"}, {"572ff12e04bcaa1900d76f00": " Defileul Rinului,"}, {"572ff12e04bcaa1900d76f02": " numeroasele sale castele și podgorii."}, {"572ff12e04bcaa1900d76f03": " „Rinul romantic”,"}, {"572ff673b2c2fd1400568669": "Delta Rin-Meuse,"}, {"572ff673b2c2fd140056866a": " Millingen aan de Rijn,"}, {"572ff673b2c2fd140056866b": "Delta Rin-Meuse,"}, {"572ffd75b2c2fd14005686e5": " sfârșitul Pleistocenului"}, {"572ffd75b2c2fd14005686e6": " Pleistocenului"}, {"572ffd75b2c2fd14005686e7": " spre vest"}, {"572ffd75b2c2fd14005686e8": " 120 m"}, {"572ffd75b2c2fd14005686e9": " teren uscat,"}, {"572fffb404bcaa1900d76fef": " începând de acum 22.000,"}, {"572fffb404bcaa1900d76ff0": " dezghețe,"}, {"572fffb404bcaa1900d76ff1": " Rin"}, {"572fffb404bcaa1900d76ff2": " 13.000 BP."}, {"572fffb404bcaa1900d76ff3": " Până la 9000 BP,"}, {"57300a9a04bcaa1900d77063": "La sfârșitul Primului Război Mondial,"}, {"57300a9a04bcaa1900d77064": " 1930,"}, {"57300a9a04bcaa1900d77065": " armatei germane"}, {"57300a9a04bcaa1900d77066": " ascensiunea lui Adolf Hitler la putere."}, {"57300a9a04bcaa1900d77067": " 1936,"}, {"572fadcbb2c2fd1400568329": " Edinburgh,"}, {"572fadcbb2c2fd140056832a": " 40%"}, {"572fadcbb2c2fd140056832c": " 51,6%"}, {"572fadcbb2c2fd140056832b": " eșuat."}, {"572fadcbb2c2fd140056832d": " 32,9%"}, {"572fc6f204bcaa1900d76cf5": " comitete."}, {"572fc6f204bcaa1900d76cf6": " mai puternic"}, {"572fc6f204bcaa1900d76cf7": " nu există o cameră pentru revizuiri."}, {"572fc6f204bcaa1900d76cf8": " de a efectua anchete și de a controla legislația."}, {"572fc6f204bcaa1900d76cf9": " alte locații de pe teritoriul Scoției."}, {"572fc8a904bcaa1900d76d1f": " comitet"}, {"572fc8a904bcaa1900d76d20": " proiecte de dezvoltare la scară largă,"}, {"572fc8a904bcaa1900d76d21": " Parlamentului Scoțian"}, {"572fc8a904bcaa1900d76d22": " Comitetele pentru proiecte de lege private"}, {"572fcc43b2c2fd140056847d": "Chestiunile rezervate"}, {"572fcc43b2c2fd140056847e": " Parlamentul Scoțian"}, {"572fcc43b2c2fd140056847f": " Westminster"}, {"572fcc43b2c2fd1400568480": " Loteria Națională,"}, {"572fdb17b2c2fd140056851d": " un număr de calificări."}, {"572fdb17b2c2fd140056851e": " 1981."}, {"572fdb17b2c2fd140056851f": " peste 18 ani"}, {"572fdb17b2c2fd1400568520": " forțelor de poliție și armate"}, {"572fdb17b2c2fd1400568521": " Legea pentru sănătate mintală"}, {"572ff932a23a5019007fcbd5": " politic"}, {"572ff932a23a5019007fcbd6": " islamul,"}, {"572ff932a23a5019007fcbd7": " savanții și observatorii"}, {"572ff932a23a5019007fcbd8": " regimuri islamice non-liberale"}, {"572ff932a23a5019007fcbd9": " religia de politică."}, {"572ffe6fb2c2fd14005686ef": " islamice"}, {"572ffe6fb2c2fd14005686f2": " guvernele incompetente, ineficiente și neglijente,"}, {"572ffe6fb2c2fd14005686f0": " locuințe"}, {"572ffe6fb2c2fd14005686f3": " retorică."}, {"572ffe6fb2c2fd14005686f1": " pentru a evita cererile de zestre prohibitive și grupurilor de femei”."}, {"572ffee1947a6a140053cf14": " dreptul și filozofia"}, {"572ffee1947a6a140053cf15": " Ligii Musulmane din Întreaga Indie."}, {"572ffee1947a6a140053cf17": " Congresului Național Indian naționalist și laic de referință din India."}, {"572ffee1947a6a140053cf16": " 1908."}, {"572ffee1947a6a140053cf18": " Reconstrucția gândirii religioase în islam."}, {"57302700a23a5019007fce89": " islamic"}, {"57302700a23a5019007fce8a": " Hassan al-Turabi."}, {"57302700a23a5019007fce8b": " Frontul Național Islamic"}, {"57302700a23a5019007fce8c": " cu bani de la sisteme bancare islamice din străinătate,"}, {"57302700a23a5019007fce8d": " universitate și academia militară,"}, {"57302bd0b2c2fd14005689db": " militantă jihadistă"}, {"57302bd0b2c2fd14005689dc": " arabi suniți din Irak și Siria."}, {"57302bd0b2c2fd14005689de": " zece milioane"}, {"57302bd0b2c2fd14005689df": " recunoașterea internațională)."}, {"57302bd0b2c2fd14005689dd": " califat,"}, {"573088da069b53140083216b": " Germania"}, {"573088da069b53140083216c": " Marea Britanie"}, {"573088da069b53140083216d": " geografii politici"}, {"573088da069b53140083216e": " expansiunea era necesară pentru supraviețuirea unui stat,"}, {"573088da069b53140083216f": " spațiul unde călătorii își puteau împărtăși povestirile."}, {"57308f6b8ab72b1400f9c580": " o geografie imaginativă"}, {"57308f6b8ab72b1400f9c581": " clasificau Estul drept „irațional și înapoiat”"}, {"57308f6b8ab72b1400f9c582": " o viziune negativa"}, {"57308f6b8ab72b1400f9c583": " o masă de cunoaștere"}, {"57308f6b8ab72b1400f9c584": " lucrări textuale și vizuale"}, {"573093598ab72b1400f9c5ae": "Imperialismul cultural"}, {"573093598ab72b1400f9c5af": " puterea sa subtilă,"}, {"573093598ab72b1400f9c5b0": " Dallas"}, {"573093598ab72b1400f9c5b1": " beneficiilor și luxurilor culturii și stilului de viață roman"}, {"573093598ab72b1400f9c5b2": " interzicerea culturii populare străine,"}, {"57309ef18ab72b1400f9c600": " aristocrație,"}, {"57309ef18ab72b1400f9c602": " anii 1950."}, {"57309ef18ab72b1400f9c601": " înainte de Primul Război Mondial,"}, {"57309ef18ab72b1400f9c603": " reformele sociale domestice"}, {"57309ef18ab72b1400f9c604": " înlăturarea fundamentului său economic."}, {"5730a4d02461fd1900a9cf29": " 1830,"}, {"5730a4d02461fd1900a9cf2a": " după 1850,"}, {"5730a4d02461fd1900a9cf2d": " catolicismului."}, {"5730a4d02461fd1900a9cf2b": " Africa de Nord și Vest, precum și Asia de Sud-Est,"}, {"5730a4d02461fd1900a9cf2c": " Germania"}, {"57309921396df919000961f6": " mijlocul secolului 18"}, {"57309921396df919000961f7": " Bisericii Anglicane."}, {"57309921396df919000961f8": " studiul Bibliei, opinii și stilul de viață disciplinat."}, {"5730b2312461fd1900a9cfad": " Grupul Operativ al Metodiștilor Uniți"}, {"5730b2312461fd1900a9cfae": " 2012,"}, {"5730b2312461fd1900a9cfaf": " Rev. Paul T. Stallsworth,"}, {"5730b2ac2461fd1900a9cfb3": " cumpătare."}, {"5730b2ac2461fd1900a9cfb6": " 2011 și 2012,"}, {"5730b2ac2461fd1900a9cfb4": " „Utilitatea Banilor”"}, {"5730b2ac2461fd1900a9cfb5": " suc nefermentat de struguri"}, {"5730b9852461fd1900a9cff9": " serviciului militar"}, {"5730b9852461fd1900a9cffa": " calea acțiunii militare"}, {"5730b9852461fd1900a9cffb": " războaielor sau unui război anume"}, {"5730d26fb54a4f140068cc94": " John Wesley,"}, {"5730d26fb54a4f140068cc95": " pastori"}, {"5730d26fb54a4f140068cc96": " Ordin al Conferinței Anuale a Erudiților."}, {"5730d26fb54a4f140068cc97": " Ordin al Conferinței Anuale a Erudiților."}, {"5733d4c8d058e614000b6353": " 1756"}, {"5733d4c8d058e614000b6354": " șase ani,"}, {"5733d4c8d058e614000b6355": " 1760."}, {"5733d4c8d058e614000b6356": " Bătălia de la Jumonville Glen"}, {"5733d68ed058e614000b637f": " 20 la 1,"}, {"5733d68ed058e614000b6380": " coastei de est a continentului,"}, {"5733d68ed058e614000b6381": " populația era centrată de-a lungul coastei,"}, {"5733f1784776f41900661575": " 40"}, {"5733f1784776f41900661576": " primele luni ale anului 1754"}, {"5733f1784776f41900661577": " Fortul Duquesne."}, {"5733f309d058e614000b6648": " i-au luat prin surprindere"}, {"5733f309d058e614000b6649": " Joseph Coulon de Jumonville,"}, {"5733f309d058e614000b664a": " Aceștia tindeau să îi sprijine pe francezi,"}, {"5733fb7bd058e614000b66ff": " Generalul-Maior James Abercrombie"}, {"5733fb7bd058e614000b6700": " Generalul-Maior Louis-Joseph de Montcalm"}, {"5733fb7bd058e614000b6701": " 18 mai 1756,"}, {"57373d0cc3c5551400e51e85": "Aristotel"}, {"57373d0cc3c5551400e51e86": " cosmologiei aristoteliene."}, {"57373d0cc3c5551400e51e87": " patru"}, {"57373d0cc3c5551400e51e88": " Pământ,"}, {"57373d0cc3c5551400e51e89": " nenaturală"}, {"5737821cc3c5551400e51f19": " Isaac Newton"}, {"5737821cc3c5551400e51f1a": " secolul 20,"}, {"5737821cc3c5551400e51f1b": " modele de unificare"}, {"5737821cc3c5551400e51f1c": " Formularea completă a modelului standard"}, {"57378b141c4567190057449f": " relativitatea generală"}, {"57378b141c456719005744a0": " liniei drepte"}, {"57378b141c456719005744a1": " „forța gravitațională”."}, {"57378b141c456719005744a2": " global"}, {"57378c9b1c456719005744a8": " Legea lui Lorentz,"}, {"57378c9b1c456719005744a9": " electrostatică"}, {"57378c9b1c456719005744a7": " Legea lui Lorentz,"}, {"57378c9b1c456719005744aa": " (datorită câmpului magnetic)."}, {"5737a25ac3c5551400e51f51": " Tensorul de stres"}, {"5737a25ac3c5551400e51f52": " tensorul de stres."}, {"5737a25ac3c5551400e51f53": " termeni de presiune"}, {"5737a25ac3c5551400e51f54": " tensorul de stres."}]